{
  "links": [
    {
      "id": 1,
      "url": "https://otter.ai/u/eYaJtiWiq7hvFo-Ll27ebCGejdI?utm_source=copy_url",
      "comment": "45 min",
      "created_at": "2026-01-16T00:00:00",
      "updated_at": "2026-01-20T02:29:25.268849"
    },
    {
      "id": 2,
      "url": "https://otter.ai/u/wPVjBrqtQlrnQAq2no8InRlrI-k",
      "comment": "",
      "created_at": "2026-01-16T00:00:00"
    },
    {
      "id": 3,
      "url": "https://otter.ai/u/ss7rwRFyQmdRtFE1g3FBiOEjejE?utm_source=copy_url",
      "comment": "",
      "created_at": "2026-01-16T00:00:00"
    },
    {
      "id": 4,
      "url": "https://otter.ai/u/PT73MxCP_Q7oTEelwHQyCDKiI78?utm_source=copy_url",
      "comment": "26 min",
      "created_at": "2026-01-16T00:00:00",
      "updated_at": "2026-01-20T12:59:24.993266"
    },
    {
      "id": 5,
      "url": "https://otter.ai/u/70fXNZNb5Az4mhV5_1cu5oVA2y8?utm_source=copy_url",
      "comment": "29 min",
      "created_at": "2026-01-16T00:00:00",
      "updated_at": "2026-01-20T13:40:34.748673"
    },
    {
      "id": 6,
      "url": "https://otter.ai/u/QDB2zXhXpvpy0EuD2iKWHlBDCag",
      "comment": "",
      "created_at": "2026-01-16T00:00:00"
    },
    {
      "id": 7,
      "url": "https://otter.ai/u/7MakzFwn9xZP1XFcYghokoqm3sY",
      "comment": "",
      "created_at": "2026-01-16T00:00:00"
    },
    {
      "id": 8,
      "url": "https://otter.ai/u/xuZyWqlFH0hyPSZiXE_2DVh1sdM?utm_source=copy_url",
      "comment": "55 min",
      "created_at": "2026-01-16T00:00:00",
      "updated_at": "2026-01-20T17:58:19.553079"
    },
    {
      "id": 9,
      "url": "https://otter.ai/u/uqj526y_fCqtU4YVnRFZ5kPPlB0?utm_source=copy_url",
      "comment": "16 min",
      "created_at": "2026-01-16T00:00:00",
      "updated_at": "2026-01-20T18:30:14.642105"
    },
    {
      "id": 10,
      "url": "https://otter.ai/u/Pbes87xocTHzo8GbVg7h3fdFrfQ?utm_source=copy_url",
      "comment": "40 min",
      "created_at": "2026-01-16T00:00:00",
      "updated_at": "2026-01-20T18:30:31.225672"
    },
    {
      "id": 11,
      "url": "https://otter.ai/u/-CdKVUXbKxY1Hyy5m5-El4WX6bs",
      "comment": "ri",
      "created_at": "2026-01-16T00:00:00"
    },
    {
      "id": 12,
      "url": "https://otter.ai/u/y7jkHWB4TGgzWP99PA3q0_vBGR8?utm_source=copy_url",
      "comment": "",
      "created_at": "2026-01-16T00:00:00"
    },
    {
      "id": 13,
      "url": "https://otter.ai/u/PKk1-7tjDiWf0zdpU_buiPZxuQk?utm_source=copy_url",
      "comment": "",
      "created_at": "2026-01-16T00:00:00"
    },
    {
      "id": 14,
      "url": "https://otter.ai/u/9sM114t9UWWV9VJvHaQEwZ_RfPc?utm_source=copy_url",
      "comment": "",
      "created_at": "2026-01-16T00:00:00"
    },
    {
      "id": 15,
      "url": "https://otter.ai/u/QSWIi1m4Xx1ISjfD_G6rONEd1D4?utm_source=copy_url",
      "comment": "",
      "created_at": "2026-01-16T00:00:00"
    },
    {
      "id": 16,
      "url": "https://otter.ai/u/Py2qlMDHDlVf7jTwEvLFqqlLjrE?utm_source=copy_url",
      "comment": "",
      "created_at": "2026-01-16T00:00:00"
    },
    {
      "id": 17,
      "url": "https://otter.ai/u/cF7uSD8Knufn12dAcb7nuWybUJY?utm_source=copy_url",
      "comment": "",
      "created_at": "2026-01-16T00:00:00"
    },
    {
      "id": 18,
      "url": "https://otter.ai/u/dPlvCfbAghSSLKsXj6lmHI52EsA?utm_source=copy_url",
      "comment": "",
      "created_at": "2026-01-16T00:00:00"
    },
    {
      "id": 19,
      "url": "https://otter.ai/u/R3w5EYJlU3E8g-ApBTRvA1OzVmM?utm_source=copy_url",
      "comment": "",
      "created_at": "2026-01-16T00:00:00"
    },
    {
      "id": 20,
      "url": "https://otter.ai/u/pMu-NTikrJZsQvA_KOcXEjCie0g?utm_source=copy_url",
      "comment": "workable",
      "created_at": "2026-01-16T00:00:00"
    },
    {
      "id": 21,
      "url": "https://otter.ai/u/8JDGOHIykVA8hBF16hzgvkr2A_E",
      "comment": "siri",
      "created_at": "2026-01-16T00:00:00"
    },
    {
      "id": 22,
      "url": "https://otter.ai/u/gyTgMpx8QyywM20q3ROF_XdyE20",
      "comment": "1 hr siri",
      "created_at": "2026-01-16T00:00:00",
      "updated_at": "2026-01-20T00:12:34.289845"
    },
    {
      "id": 23,
      "url": "https://otter.ai/u/PPpifIquG6atqBcrSpvkbfJJHd4",
      "comment": "45 MIN SIRI",
      "created_at": "2026-01-16T00:00:00",
      "updated_at": "2026-01-19T23:32:10.461223"
    },
    {
      "id": 24,
      "url": "https://otter.ai/u/M4oDcGWQ3IMGGkG7GnBwJrFnH9Y?utm_source=copy_url",
      "comment": "sahul.net",
      "created_at": "2026-01-16T00:00:00"
    },
    {
      "id": 25,
      "url": "https://otter.ai/u/t5_SUv7ZvS1M6_88qTVfAuC-puA",
      "comment": "santhosh, 26 min",
      "created_at": "2026-01-16T00:00:00",
      "updated_at": "2026-01-19T17:06:38.902205"
    },
    {
      "id": 26,
      "url": "https://otter.ai/u/dD0sBEo7OZUhFSNJo4yksX9F3Tc?utm_source=copy_url",
      "comment": "19 min",
      "created_at": "2026-01-16T00:00:00",
      "updated_at": "2026-01-19T17:06:13.323132"
    },
    {
      "id": 27,
      "url": "https://otter.ai/u/0F0keRUuTMKPnnnrWC5N_yvcLuA",
      "comment": "1hr",
      "created_at": "2026-01-16T00:00:00",
      "updated_at": "2026-01-19T16:55:16.036381"
    },
    {
      "id": 28,
      "url": "https://otter.ai/u/Kr0LizPou-yAM2ntdwwJO4Gowcs?tab=chat&view=summary",
      "comment": "25 MIN",
      "created_at": "2026-01-16T00:00:00",
      "updated_at": "2026-01-19T14:49:03.541898"
    },
    {
      "id": 29,
      "url": "https://otter.ai/u/rzxFggfj8EQtXbFEf8iaFbyyvOw",
      "comment": "17 MIN",
      "created_at": "2026-01-16T00:00:00",
      "updated_at": "2026-01-19T14:48:46.992444"
    },
    {
      "id": 30,
      "url": "https://otter.ai/u/vfPJNaQGoxcldhDOtJL3vHjs8ZA?utm_source=copy_url",
      "comment": "preethi referencw 2 hr",
      "created_at": "2026-01-20T23:51:32.703990"
    }
  ]
}